carambola_sch/__init__.py
carambola_sch-0.1.0.dist-info/METADATA
carambola_sch-0.1.0.dist-info/WHEEL
carambola_sch-0.1.0.dist-info/RECORD
