Metadata-Version: 2.1
Name: carambola-sch
Version: 0.1.0
Summary: 
Author: Marcelo Schneider
Author-email: schenider.fei@gmail.com
Requires-Python: >=3.10,<4.0
Classifier: Programming Language :: Python :: 3
Classifier: Programming Language :: Python :: 3.10
Classifier: Programming Language :: Python :: 3.11
Requires-Dist: authlib (>=1.2.1,<2.0.0)
Requires-Dist: requests (>=2.31.0,<3.0.0)
